{"mean":{"confidence_interval":{"confidence_level":0.99,"lower_bound":1385219.6279821931,"upper_bound":1409336.2973967039},"point_estimate":1396128.9941485417,"standard_error":4590.686149127666},"median":{"confidence_interval":{"confidence_level":0.99,"lower_bound":1375335.1875,"upper_bound":1387777.9641657334},"point_estimate":1378760.3221986569,"standard_error":2502.6126074969657},"median_abs_dev":{"confidence_interval":{"confidence_level":0.99,"lower_bound":10131.970730240953,"upper_bound":33803.77359986311},"point_estimate":18471.1974399277,"standard_error":4508.1246639155215},"slope":{"confidence_interval":{"confidence_level":0.99,"lower_bound":1379548.6687029346,"upper_bound":1398414.855658456},"point_estimate":1387781.8434284024,"standard_error":3695.166617752504},"std_dev":{"confidence_interval":{"confidence_level":0.99,"lower_bound":30268.747607749305,"upper_bound":62287.975858504644},"point_estimate":45651.01562092663,"standard_error":6393.667558154846}}